[
  {
    "id": 1,
    "title": "News Homepage",
    "technologies": ["HTML", "CSS", "JavaScript", "React"],
    "img": {
      "avif": "",
      "webp": "",
      "png": "projects/home_page.png",
      "alt": "News Homepage"
    },
    "urls": {
      "repository": "https://github.com/jhonnymosquera/news-homepage",
      "live": "https://news-homepage-jjmm.netlify.app/"
    }
  },
  {
    "id": 2,
    "title": "News Homepage",
    "technologies": ["HTML", "CSS", "JavaScript", "React"],
    "img": {
      "avif": "",
      "webp": "",
      "png": "projects/tip_calculator.png",
      "alt": "News Homepage"
    },
    "urls": {
      "repository": "https://github.com/jhonnymosquera/news-homepage",
      "live": "https://news-homepage-jjmm.netlify.app/"
    }
  }
]
